asonic
