Metadata-Version: 2.1
Name: asonic
Version: 1.0.1
Summary: Async python client for Sonic database
Home-page: https://github.com/moshe/asonic
Author: Moshe Zada
License: UNKNOWN
Keywords: asonic,sonic,search,asyncio,async,text
Platform: UNKNOWN
Provides-Extra: tests
